{"duration": 0.01656508445739746, "input_args": {"transformer": "PCA(n_components=15)", "X": "array([[ 0.67958305,  1.00838501,  0.39708376, ...,  1.45847331,\n         0.3612422 , -0.72937255],\n       [ 1.6474328 ,  1.97825427,  1.54525183, ...,  0.79968833,\n        -1.26221557, -1.53120598],\n       [-1.13513522,  0.03851576, -1.00623276, ..., -1.0668691 ,\n        -0.77517824, -0.99665036],\n       ...,\n       [-0.53022913,  0.36180551, -0.11321315, ..., -0.62767912,\n        -1.09986979, -0.32845584],\n       [-0.53022913, -1.41628812, -0.87865853, ..., -1.2864641 ,\n         0.03655064,  0.07246087],\n       [-1.014154  , -1.577933  , -1.13380699, ...,  1.12908082,\n         1.17297108,  1.0079332 ]])", "y": "['bus', 'bus', 'bus', 'bus', 'bus', 'bus', 'bus', 'bus', 'bus', 'bus', 'bus', 'bus', 'bus', 'bus', 'bus', 'bus', 'bus', 'bus', 'bus', 'bus', 'bus', 'bus', 'bus', 'bus', 'bus', 'bus', 'bus', 'bus', 'bus', 'bus', 'bus', 'bus', 'bus', 'bus', 'bus', 'bus', 'bus', 'bus', 'bus', 'bus', 'bus', 'bus', 'bus', 'bus', 'bus', 'bus', 'bus', 'bus', 'bus', 'bus', 'bus', 'bus', 'bus', 'bus', 'bus', 'bus', 'bus', 'bus', 'bus', 'bus', 'bus', 'bus', 'bus', 'bus', 'bus', 'bus', 'bus', 'bus', 'bus', 'bus', 'bus', 'bus', 'bus', 'bus', 'bus', 'bus', 'bus', 'bus', 'bus', 'bus', 'bus', 'bus', 'bus', 'bus', 'bus', 'bus', 'bus', 'bus', 'bus', 'bus', 'bus', 'bus', 'bus', 'bus', 'bus', 'bus', 'bus', 'bus', 'bus', 'bus', 'bus', 'bus', 'bus', 'bus', 'bus', 'bus', 'bus', 'bus', 'bus', 'bus', 'bus', 'bus', 'bus', 'bus', 'bus', 'bus', 'bus', 'bus', 'bus', 'bus', 'bus', 'bus', 'bus', 'bus', 'bus', 'bus', 'opel', 'opel', 'opel', 'opel', 'opel', 'opel', 'opel', 'opel', 'opel', 'opel', 'opel', 'opel', 'opel', 'opel', 'opel', 'opel', 'opel', 'opel', 'opel', 'opel', 'opel', 'opel', 'opel', 'opel', 'opel', 'opel', 'opel', 'opel', 'opel', 'opel', 'opel', 'opel', 'opel', 'opel', 'opel', 'opel', 'opel', 'opel', 'opel', 'opel', 'opel', 'opel', 'opel', 'opel', 'opel', 'opel', 'opel', 'opel', 'opel', 'opel', 'opel', 'opel', 'opel', 'opel', 'opel', 'opel', 'opel', 'opel', 'opel', 'opel', 'opel', 'opel', 'opel', 'opel', 'opel', 'opel', 'opel', 'opel', 'opel', 'opel', 'opel', 'opel', 'opel', 'opel', 'opel', 'opel', 'opel', 'opel', 'opel', 'opel', 'opel', 'opel', 'opel', 'opel', 'opel', 'opel', 'opel', 'opel', 'opel', 'opel', 'opel', 'opel', 'opel', 'opel', 'opel', 'opel', 'opel', 'opel', 'opel', 'opel', 'opel', 'opel', 'opel', 'opel', 'opel', 'opel', 'opel', 'opel', 'opel', 'opel', 'opel', 'opel', 'opel', 'opel', 'opel', 'opel', 'opel', 'opel', 'opel', 'opel', 'opel', 'opel', 'opel', 'opel', 'opel', 'opel', 'saab', 'saab', 'saab', 'saab', 'saab', 'saab', 'saab', 'saab', 'saab', 'saab', 'saab', 'saab', 'saab', 'saab', 'saab', 'saab', 'saab', 'saab', 'saab', 'saab', 'saab', 'saab', 'saab', 'saab', 'saab', 'saab', 'saab', 'saab', 'saab', 'saab', 'saab', 'saab', 'saab', 'saab', 'saab', 'saab', 'saab', 'saab', 'saab', 'saab', 'saab', 'saab', 'saab', 'saab', 'saab', 'saab', 'saab', 'saab', 'saab', 'saab', 'saab', 'saab', 'saab', 'saab', 'saab', 'saab', 'saab', 'saab', 'saab', 'saab', 'saab', 'saab', 'saab', 'saab', 'saab', 'saab', 'saab', 'saab', 'saab', 'saab', 'saab', 'saab', 'saab', 'saab', 'saab', 'saab', 'saab', 'saab', 'saab', 'saab', 'saab', 'saab', 'saab', 'saab', 'saab', 'saab', 'saab', 'saab', 'saab', 'saab', 'saab', 'saab', 'saab', 'saab', 'saab', 'saab', 'saab', 'saab', 'saab', 'saab', 'saab', 'saab', 'saab', 'saab', 'saab', 'saab', 'saab', 'saab', 'saab', 'saab', 'saab', 'saab', 'saab', 'saab', 'saab', 'saab', 'saab', 'saab', 'saab', 'saab', 'saab', 'saab', 'saab', 'saab', 'saab', 'saab', 'van', 'van', 'van', 'van', 'van', 'van', 'van', 'van', 'van', 'van', 'van', 'van', 'van', 'van', 'van', 'van', 'van', 'van', 'van', 'van', 'van', 'van', 'van', 'van', 'van', 'van', 'van', 'van', 'van', 'van', 'van', 'van', 'van', 'van', 'van', 'van', 'van', 'van', 'van', 'van', 'van', 'van', 'van', 'van', 'van', 'van', 'van', 'van', 'van', 'van', 'van', 'van', 'van', 'van', 'van', 'van', 'van', 'van', 'van', 'van', 'van', 'van', 'van', 'van', 'van', 'van', 'van', 'van', 'van', 'van', 'van', 'van', 'van', 'van', 'van', 'van', 'van', 'van', 'van', 'van', 'van', 'van', 'van', 'van', 'van', 'van', 'van', 'van', 'van', 'van', 'van', 'van', 'van', 'van', 'van', 'van', 'van', 'van', 'van', 'van', 'van', 'van', 'van', 'van', 'van', 'van', 'van', 'van', 'van', 'van', 'van', 'van', 'van', 'van', 'van', 'van', 'van', 'van', 'van', 'van', 'van', 'van', 'van', 'van', 'van', 'van']", "weight": "None", "message_clsname": "'Pipeline'", "message": "None", "**": "{}"}}