{"duration": 0.07500100135803223, "input_args": {"sampler": "RandomUnderSampler()", "X": "array([[ 0.19233488,  0.50952408,  0.05755919, ...,  0.36681194,\n        -0.30080827,  0.19128009],\n       [-0.29582937, -0.62745819,  0.12120868, ...,  0.14552075,\n         0.02573105,  0.45957557],\n       [ 1.29070444,  0.83437616,  1.52149727, ..., -0.40770721,\n        -0.13753861,  0.05713234],\n       ...,\n       [-0.05174724, -0.95231026,  0.24850764, ...,  0.47745753,\n         1.33188833,  1.1303143 ],\n       [ 0.31437594, -1.27716234, -0.51528614, ...,  0.36681194,\n         0.18900071,  0.19128009],\n       [ 1.65682763,  0.9968022 ,  1.33054883, ..., -0.96093518,\n        -0.13753861,  0.32542783]])", "y": "['van', 'van', 'saab', 'van', 'bus', 'bus', 'bus', 'van', 'van', 'saab', 'van', 'saab', 'bus', 'van', 'bus', 'opel', 'van', 'bus', 'saab', 'opel', 'bus', 'van', 'bus', 'bus', 'saab', 'van', 'saab', 'saab', 'bus', 'saab', 'van', 'saab', 'opel', 'opel', 'opel', 'van', 'bus', 'van', 'saab', 'bus', 'opel', 'van', 'van', 'saab', 'saab', 'van', 'van', 'bus', 'van', 'saab', 'saab', 'saab', 'opel', 'bus', 'bus', 'van', 'saab', 'van', 'opel', 'van', 'opel', 'opel', 'van', 'bus', 'bus', 'opel', 'bus', 'opel', 'van', 'bus', 'opel', 'opel', 'opel', 'opel', 'van', 'opel', 'saab', 'saab', 'bus', 'bus', 'bus', 'bus', 'van', 'opel', 'bus', 'bus', 'van', 'van', 'bus', 'opel', 'saab', 'opel', 'saab', 'van', 'bus', 'opel', 'saab', 'bus', 'opel', 'bus', 'bus', 'van', 'van', 'van', 'bus', 'saab', 'opel', 'opel', 'bus', 'bus', 'van', 'van', 'opel', 'opel', 'van', 'van', 'opel', 'saab', 'bus', 'bus', 'saab', 'van', 'van', 'saab', 'van', 'van', 'bus', 'bus', 'van', 'bus', 'saab', 'saab', 'saab', 'van', 'opel', 'van', 'van', 'van', 'saab', 'van', 'saab', 'bus', 'opel', 'bus', 'opel', 'opel', 'van', 'bus', 'saab', 'van', 'saab', 'bus', 'opel', 'saab', 'van', 'bus', 'opel', 'van', 'saab', 'opel', 'opel', 'opel', 'saab', 'saab', 'opel', 'opel', 'saab', 'saab', 'bus', 'van', 'opel', 'bus', 'van', 'bus', 'van', 'bus', 'opel', 'bus', 'bus', 'van', 'saab', 'opel', 'bus', 'saab', 'saab', 'bus', 'bus', 'opel', 'opel', 'opel', 'opel', 'van', 'saab', 'bus', 'saab', 'bus', 'saab', 'bus', 'bus', 'bus', 'van', 'saab', 'opel', 'opel', 'van', 'van', 'opel', 'bus', 'bus', 'opel', 'opel', 'van', 'bus', 'bus', 'opel', 'opel', 'saab', 'opel', 'bus', 'van', 'opel', 'van', 'bus', 'bus', 'saab', 'van', 'saab', 'van', 'saab', 'saab', 'van', 'saab', 'bus', 'saab', 'van', 'van', 'bus', 'bus', 'opel', 'bus', 'opel', 'opel', 'bus', 'saab', 'van', 'van', 'bus', 'saab', 'opel', 'saab', 'van', 'opel', 'van', 'bus', 'van', 'saab', 'saab', 'opel', 'saab', 'opel', 'saab', 'saab', 'van', 'van', 'saab', 'bus', 'bus', 'saab', 'van', 'van', 'bus', 'saab', 'van', 'van', 'bus', 'bus', 'bus', 'opel', 'saab', 'bus', 'opel', 'bus', 'bus', 'saab', 'van', 'saab', 'bus', 'van', 'opel', 'saab', 'van', 'van', 'bus', 'van', 'bus', 'bus', 'bus', 'saab', 'saab', 'bus', 'saab', 'opel', 'bus', 'van', 'bus', 'bus', 'saab', 'opel', 'opel', 'opel', 'saab', 'van', 'bus', 'opel', 'bus', 'van', 'van', 'saab', 'van', 'bus', 'saab', 'bus', 'bus', 'saab', 'saab', 'bus', 'opel', 'opel', 'van', 'saab', 'van', 'opel', 'opel', 'bus', 'bus', 'saab', 'van', 'bus', 'van', 'bus', 'bus', 'opel', 'saab', 'opel', 'opel', 'bus', 'saab', 'opel', 'van', 'opel', 'opel', 'saab', 'van', 'bus', 'saab', 'opel', 'bus', 'saab', 'opel', 'opel', 'saab', 'saab', 'saab', 'van', 'opel', 'saab', 'van', 'saab', 'bus', 'opel', 'bus', 'bus', 'van', 'bus', 'van', 'bus', 'saab', 'saab', 'saab', 'opel', 'opel', 'bus', 'bus', 'opel', 'opel', 'van', 'saab', 'van', 'van', 'opel', 'bus', 'van', 'van', 'bus', 'saab', 'opel', 'bus', 'bus', 'bus', 'van', 'saab', 'opel', 'opel', 'van', 'opel', 'bus', 'opel', 'saab', 'bus', 'saab', 'saab', 'opel', 'bus', 'opel', 'van', 'opel', 'bus', 'bus', 'bus', 'saab', 'van', 'opel', 'saab', 'bus', 'opel', 'opel', 'opel', 'opel', 'saab', 'van', 'saab', 'bus', 'saab', 'bus', 'saab', 'van', 'van', 'opel', 'opel', 'saab', 'saab', 'van', 'van', 'opel', 'bus', 'van', 'saab', 'opel', 'bus', 'van', 'bus', 'opel', 'opel', 'bus', 'saab', 'bus', 'van', 'van', 'opel', 'saab', 'van', 'opel', 'opel', 'opel', 'bus', 'bus', 'bus', 'opel', 'saab', 'van', 'van', 'opel', 'bus', 'opel', 'opel', 'saab', 'opel', 'van', 'bus', 'bus', 'saab', 'opel', 'opel', 'van', 'van', 'bus', 'opel', 'saab', 'opel', 'opel', 'saab', 'saab', 'bus', 'opel', 'bus', 'bus', 'opel', 'van', 'van', 'opel', 'opel', 'opel', 'opel', 'saab', 'opel', 'saab', 'saab', 'opel', 'van', 'opel', 'bus', 'opel', 'opel', 'saab', 'van', 'opel', 'opel', 'saab', 'saab', 'van', 'saab', 'van', 'saab', 'opel', 'saab', 'saab', 'opel', 'saab', 'saab', 'saab', 'saab', 'saab', 'saab']", "message_clsname": "'Pipeline'", "message": "None", "**": "{}"}}